pb_checker/__init__.py
pb_checker/pb.py
pb_checker-1.0.2.dist-info/licenses/LICENSE
pb_checker-1.0.2.dist-info/METADATA
pb_checker-1.0.2.dist-info/WHEEL
pb_checker-1.0.2.dist-info/top_level.txt
pb_checker-1.0.2.dist-info/RECORD
